distwq.py
distwq-1.2.1.dist-info/METADATA
distwq-1.2.1.dist-info/WHEEL
distwq-1.2.1.dist-info/licenses/LICENSE
distwq-1.2.1.dist-info/RECORD
