Metadata-Version: 2.4
Name: distwq
Version: 1.2.1
Summary: Distributed queue operations with mpi4py
Author-email: Ivan Raikov <ivan.g.raikov@gmail.com>
License-Expression: GPL-3.0-or-later
License-File: LICENSE
Keywords: MPI,distributed computing,distributed queue,mpi4py
Requires-Python: >=3.9
Requires-Dist: mpi4py>=4.0.0
Requires-Dist: numpy>=1.26.2
Requires-Dist: ruff>=0.6.9
